odoo9_addon_l10n_it_rea-9.0.0.1.0.99.dev15-py2.7-nspkg.pth
odoo9_addon_l10n_it_rea-9.0.0.1.0.99.dev15.dist-info/DESCRIPTION.rst
odoo9_addon_l10n_it_rea-9.0.0.1.0.99.dev15.dist-info/METADATA
odoo9_addon_l10n_it_rea-9.0.0.1.0.99.dev15.dist-info/RECORD
odoo9_addon_l10n_it_rea-9.0.0.1.0.99.dev15.dist-info/WHEEL
odoo9_addon_l10n_it_rea-9.0.0.1.0.99.dev15.dist-info/metadata.json
odoo9_addon_l10n_it_rea-9.0.0.1.0.99.dev15.dist-info/namespace_packages.txt
odoo9_addon_l10n_it_rea-9.0.0.1.0.99.dev15.dist-info/top_level.txt
odoo_addons/l10n_it_rea/README.rst
odoo_addons/l10n_it_rea/__init__.py
odoo_addons/l10n_it_rea/__openerp__.py
odoo_addons/l10n_it_rea/partner_view.xml
odoo_addons/l10n_it_rea/res_partner.py
odoo_addons/l10n_it_rea/i18n/am.po
odoo_addons/l10n_it_rea/i18n/ar.po
odoo_addons/l10n_it_rea/i18n/bg.po
odoo_addons/l10n_it_rea/i18n/bs.po
odoo_addons/l10n_it_rea/i18n/ca.po
odoo_addons/l10n_it_rea/i18n/cs.po
odoo_addons/l10n_it_rea/i18n/da.po
odoo_addons/l10n_it_rea/i18n/de.po
odoo_addons/l10n_it_rea/i18n/el_GR.po
odoo_addons/l10n_it_rea/i18n/en_GB.po
odoo_addons/l10n_it_rea/i18n/es.po
odoo_addons/l10n_it_rea/i18n/es_CR.po
odoo_addons/l10n_it_rea/i18n/es_EC.po
odoo_addons/l10n_it_rea/i18n/es_MX.po
odoo_addons/l10n_it_rea/i18n/es_VE.po
odoo_addons/l10n_it_rea/i18n/et.po
odoo_addons/l10n_it_rea/i18n/eu.po
odoo_addons/l10n_it_rea/i18n/fi.po
odoo_addons/l10n_it_rea/i18n/fr.po
odoo_addons/l10n_it_rea/i18n/fr_CA.po
odoo_addons/l10n_it_rea/i18n/fr_CH.po
odoo_addons/l10n_it_rea/i18n/gl.po
odoo_addons/l10n_it_rea/i18n/hr.po
odoo_addons/l10n_it_rea/i18n/hr_HR.po
odoo_addons/l10n_it_rea/i18n/hu.po
odoo_addons/l10n_it_rea/i18n/id.po
odoo_addons/l10n_it_rea/i18n/it.po
odoo_addons/l10n_it_rea/i18n/ja.po
odoo_addons/l10n_it_rea/i18n/l10n_it_rea.pot
odoo_addons/l10n_it_rea/i18n/lt.po
odoo_addons/l10n_it_rea/i18n/lv.po
odoo_addons/l10n_it_rea/i18n/mk.po
odoo_addons/l10n_it_rea/i18n/mn.po
odoo_addons/l10n_it_rea/i18n/nb.po
odoo_addons/l10n_it_rea/i18n/nb_NO.po
odoo_addons/l10n_it_rea/i18n/nl.po
odoo_addons/l10n_it_rea/i18n/nl_BE.po
odoo_addons/l10n_it_rea/i18n/pl.po
odoo_addons/l10n_it_rea/i18n/pt.po
odoo_addons/l10n_it_rea/i18n/pt_BR.po
odoo_addons/l10n_it_rea/i18n/pt_PT.po
odoo_addons/l10n_it_rea/i18n/ro.po
odoo_addons/l10n_it_rea/i18n/ru.po
odoo_addons/l10n_it_rea/i18n/sk.po
odoo_addons/l10n_it_rea/i18n/sl.po
odoo_addons/l10n_it_rea/i18n/sr@latin.po
